{
    "tile.info_update.name": "update!",
    "tile.info_update2.name": "ate!upd",
    "tile.glowingobsidian.name": "发光的黑曜石",
    "tile.end_gateway.name": "终端网关",
    "tile.end_portal.name": "终端门户",
    "tile.reserved6.name": "保留6",
    "tile.bubble_column.name": "气泡柱子",
    "tile.lava.name": "熔岩",
    "tile.movingBlock.name": "36号方块",
    "tile.pistonArmCollision.name": "↓↑臂",
    "tile.wall_banner.name": "墙上的旗帜",
    "tile.wall_sign.name": "墙上的搞事牌",
    "tile.melon_stem.name": "西瓜梗",
    "tile.daylight_detector_inverted.name": "反向电荷耦合器件",
    "tile.double_wooden_slab.oak.name": "橡木半砖",
    "tile.blackstone_double_slab.name": "非洲石头半砖",
    "tile.polished_blackstone_brick_double_slab.name": "使用了打磨工艺进行加工的非洲石头半砖",
    "craftingScreen.tab.none": "调试"
}